{
  "normalizationProfile": "LowercaseRemovePeriods",
  "cardinalMap": {
    "viens": 1,
    "divi": 2,
    "trīs": 3,
    "tris": 3,
    "četri": 4,
    "cetri": 4,
    "pieci": 5,
    "seši": 6,
    "sesi": 6,
    "septiņi": 7,
    "septini": 7,
    "astoņi": 8,
    "astoni": 8,
    "deviņi": 9,
    "devini": 9,
    "desmit": 10,
    "vienpadsmit": 11,
    "divpadsmit": 12,
    "trīspadsmit": 13,
    "trispadsmit": 13,
    "četrpadsmit": 14,
    "cetrpadsmit": 14,
    "piecpadsmit": 15,
    "sešpadsmit": 16,
    "sespadsmit": 16,
    "septiņpadsmit": 17,
    "septinpadsmit": 17,
    "astoņpadsmit": 18,
    "astonpadsmit": 18,
    "deviņpadsmit": 19,
    "devinpadsmit": 19,
    "divdesmit": 20,
    "trīsdesmit": 30,
    "trisdesmit": 30,
    "četrdesmit": 40,
    "cetrdesmit": 40,
    "piecdesmit": 50,
    "sešdesmit": 60,
    "sesdesmit": 60,
    "septiņdesmit": 70,
    "septindesmit": 70,
    "astoņdesmit": 80,
    "astondesmit": 80,
    "deviņdesmit": 90,
    "devindesmit": 90,
    "simts": 100,
    "simtu": 100,
    "simti": 100,
    "tūkstotis": 1000,
    "tukstotis": 1000,
    "tūkstoš": 1000,
    "tukstos": 1000,
    "tūkstoši": 1000,
    "tukstosi": 1000,
    "miljons": 1000000,
    "miljoni": 1000000
  },
  "useHundredMultiplier": true
}

